ensdg/__init__.py
ensdg/boundary.py
ensdg/canon.py
ensdg/cli.py
ensdg/digest.py
ensdg/example_governance.py
ensdg/example_rules.py
ensdg/invariants.py
ensdg/model.py
ensdg/replay.py
ensdg/runner.py
ensdg/stream.py
ensdg-0.4.0.dist-info/licenses/LICENSE
ensdg-0.4.0.dist-info/METADATA
ensdg-0.4.0.dist-info/WHEEL
ensdg-0.4.0.dist-info/entry_points.txt
ensdg-0.4.0.dist-info/top_level.txt
ensdg-0.4.0.dist-info/RECORD
