Metadata-Version: 2.4
Name: ensdg
Version: 0.4.0
Summary: Reference-grade DBL implementation: deterministic governance over non-deterministic execution.
Requires-Python: >=3.10
License-File: LICENSE
Dynamic: license-file
